Metadata-Version: 1.0
Name: slimpoint
Version: 1.0.7
Summary: Slim, readable, expressive interactions with backend services
Home-page: https://github.com/brandonblair/slimpoint
Author: Brandon Blair
Author-email: cbrandon.blair@gmail.com
License: UNKNOWN
Platform: UNKNOWN
